{
  "slug": "dock",
  "name": "Dock Community",
  "bundleIdentifier": "community.pock.widgets.dock",
  "version": "1.4.3",
  "artifact": "DockCommunity",
  "releaseTag": "dock-community-1.4.3",
  "releaseTitle": "Dock Community 1.4.3",
  "changelog": "Keeps running app state in sync so closed apps disappear smoothly and running-only Dock layouts stay current.",
  "coreMin": "0.10.0-5",
  "enabledByDefault": true,
  "workspace": "Dock.xcworkspace",
  "scheme": "Dock",
  "pockName": "Dock.pock",
  "requiresMediaRemoteAdapter": false,
  "licenseStatus": "MIT_REQUIRED"
}
